BabelGladeExtractor-0.4.dist-info/DESCRIPTION.rst
BabelGladeExtractor-0.4.dist-info/METADATA
BabelGladeExtractor-0.4.dist-info/RECORD
BabelGladeExtractor-0.4.dist-info/WHEEL
BabelGladeExtractor-0.4.dist-info/entry_points.txt
BabelGladeExtractor-0.4.dist-info/metadata.json
BabelGladeExtractor-0.4.dist-info/top_level.txt
babelglade/__init__.py
babelglade/extract.py
babelglade/translate.py
