Metadata-Version: 2.0
Name: BabelGladeExtractor
Version: 0.4
Summary: Babel Glade XML files translatable strings extractor
Home-page: https://github.com/GNOME-Keysign/babel-glade
Author: Pedro Algarvio
Author-email: ufs@ufsoft.org
License: BSD
Keywords: PyGTK,Glade,gettext,Babel,I18n,L10n
Platform: UNKNOWN
Requires-Dist: Babel
Requires-Dist: lxml
